AUTHORS
LICENSE
MANIFEST.in
README.md
setup.py
Axilent_Dox.egg-info/PKG-INFO
Axilent_Dox.egg-info/SOURCES.txt
Axilent_Dox.egg-info/dependency_links.txt
Axilent_Dox.egg-info/requires.txt
Axilent_Dox.egg-info/top_level.txt
dox/__init__.py
dox/client.py
dox/commands.py
dox/config.py
dox/uploader.py
dox/utils.py
scripts/dox