Metadata-Version: 1.0
Name: Axilent-Dox
Version: 0.1.4
Summary: Markdown-oriented content authoring for Axilent.
Home-page: https://github.com/Axilent/Dox
Author: Loren Davie
Author-email: code@axilent.com
License: BSD
Platform: UNKNOWN
Classifier: Development Status :: 2 - Pre-Alpha
Classifier: Environment :: Console
Classifier: Intended Audience :: End Users/Desktop
Classifier: License :: OSI Approved :: BSD License
Classifier: Programming Language :: Python
Classifier: Topic :: Text Processing
